jragbeer_common/__init__.py
jragbeer_common/azure/__init__.py
jragbeer_common/azure/jragbeer_common_azure.py
jragbeer_common/common/__init__.py
jragbeer_common/common/jragbeer_common_data_eng.py
jragbeer_common/dask/__init__.py
jragbeer_common/dask/jragbeer_common_dask.py
jragbeer_common/db/__init__.py
jragbeer_common/db/jragbeer_common_db.py
jragbeer_common/ubuntu/__init__.py
jragbeer_common/ubuntu/jragbeer_common_ubuntu.py
jragbeer_common-0.2.59.dist-info/licenses/LICENSE
jragbeer_common-0.2.59.dist-info/METADATA
jragbeer_common-0.2.59.dist-info/WHEEL
jragbeer_common-0.2.59.dist-info/top_level.txt
jragbeer_common-0.2.59.dist-info/RECORD
