Metadata-Version: 2.4
Name: jragbeer_common
Version: 0.2.59
Summary: Package to create JRAGBEER Common Functions
Author-email: jragbeer <jragbeer@gmail.com>
Classifier: Programming Language :: Python :: 3
Classifier: License :: OSI Approved :: MIT License
Classifier: Operating System :: OS Independent
Requires-Python: <3.13,>=3.12
License-File: LICENSE
Requires-Dist: dask==2025.11.0
Requires-Dist: distributed==2025.11.0
Requires-Dist: urllib3==2.2.1
Requires-Dist: psycopg2-binary>=2.9.10
Requires-Dist: polars>=1.36.0
Requires-Dist: pyarrow==18.1.0
Requires-Dist: beautifulsoup4==4.12.2
Requires-Dist: pandas==2.2.2
Requires-Dist: selenium==4.28.1
Requires-Dist: SQLAlchemy==2.0.23
Requires-Dist: tqdm==4.66.1
Requires-Dist: numpy==1.26.0
Requires-Dist: paramiko==3.5.0
Requires-Dist: requests==2.31.0
Requires-Dist: azure-storage-blob==12.16.0
Requires-Dist: azure-core==1.26.4
Requires-Dist: pre-commit>=4.1.0
Requires-Dist: types-paramiko>=3.5.0.20240928
Requires-Dist: types-pyyaml>=6.0.12.20241230
Dynamic: license-file
